manual_tests/__init__.py
manual_tests/data.py
manual_tests/datacategories.py
manual_tests/datasets.py
manual_tests/datatypes.py
manual_tests/locationcategories.py
manual_tests/locations.py
manual_tests/log_setup.py
manual_tests/run_manual_tests.py
manual_tests/stations.py
manual_tests/validate_json.py
noaa_cdo_api/__init__.py
noaa_cdo_api/json_responses.py
noaa_cdo_api/json_schemas.py
noaa_cdo_api/noaa.py
noaa_cdo_api/parameter_schemas.py
noaa_cdo_api/py.typed
noaa_cdo_api-0.0.3.dist-info/licenses/LICENSE
noaa_cdo_api-0.0.3.dist-info/METADATA
noaa_cdo_api-0.0.3.dist-info/WHEEL
noaa_cdo_api-0.0.3.dist-info/top_level.txt
noaa_cdo_api-0.0.3.dist-info/RECORD
