Metadata-Version: 2.4
Name: noaa-cdo-api
Version: 0.0.3
Summary: A NOAA NCEI API wrapper for weather data
Author-email: fxf8 <fuex9follets@gmail.com>
License-Expression: MIT
Project-URL: Homepgae, https://github.com/fxf8/noaa-cdo-api
Project-URL: Documentation, https://fxf8.github.io/noaa-cdo-api/noaa_api.html
Project-URL: Issues, https://github.com/fxf8/noaa-cdo-api/issues
Requires-Python: >=3.12
License-File: LICENSE
Requires-Dist: aiohttp>=3.11.14
Requires-Dist: aiolimiter>=1.2.1
Requires-Dist: requests>=2.32.3
Requires-Dist: rich>=14.0.0
Requires-Dist: setuptools>=78.1.0
Requires-Dist: yarl>=1.18.3
Dynamic: license-file
